{
  "courses": [
    {
      "name": "Motivational Speaking",
      "description": "Learn to motivate those around you",
      "location": "Brussels",
      "teacher": "Logan",
      "date": "2001-03-03",
      "timeStart": "10:00",
      "timeEnd": "19:00",
      "id": 2
    },
    {
      "name": "Python",
      "description": "Learn to use Python to create games",
      "location": "Brussels",
      "teacher": "Logan",
      "date": "2025-04-07",
      "timeStart": "11:00",
      "timeEnd": "17:00",
      "id": 4
    },
    {
      "name": "CSS3",
      "description": "Make websites pretty",
      "location": "Antwerpen",
      "teacher": "Mrs Laurence",
      "date": "2025-04-28",
      "timeStart": "19:44",
      "timeEnd": "00:44",
      "id": 5
    },
    {
      "name": "Water Filtering",
      "description": "Filter water by putting in some stones and then putting in some sand and then putting in some gravel",
      "location": "Antwerpen",
      "teacher": "zdh",
      "date": "2025-05-05",
      "timeStart": "19:44",
      "timeEnd": "05:44",
      "id": 6
    },
    {
      "name": "Latin",
      "description": "\"Lorem ipsum dolor sit  ",
      "location": "Antwerpen",
      "teacher": "afsdg",
      "date": "2025-05-01",
      "timeStart": "18:46",
      "timeEnd": "19:46",
      "id": 7
    },
    {
      "name": "eryerythye",
      "description": "WERWER",
      "location": "Leuven",
      "teacher": "EARERT",
      "date": "2025-04-07",
      "timeStart": "09:00",
      "timeEnd": "17:59",
      "id": 8
    }
  ]
}